odoo/addons/project_task_sign/README.rst
odoo/addons/project_task_sign/__init__.py
odoo/addons/project_task_sign/__manifest__.py
odoo/addons/project_task_sign/controllers/__init__.py
odoo/addons/project_task_sign/controllers/portal.py
odoo/addons/project_task_sign/controllers/project.py
odoo/addons/project_task_sign/data/mail_template_data.xml
odoo/addons/project_task_sign/i18n/es.po
odoo/addons/project_task_sign/models/__init__.py
odoo/addons/project_task_sign/models/account_analytic_line.py
odoo/addons/project_task_sign/models/project_project.py
odoo/addons/project_task_sign/models/project_task.py
odoo/addons/project_task_sign/report/report_timesheet_template.xml
odoo/addons/project_task_sign/static/description/icon.png
odoo/addons/project_task_sign/views/project_portal_templates.xml
odoo/addons/project_task_sign/views/project_views.xml
odoo_addon_project_task_sign-16.0.1.0.0.7.dist-info/METADATA
odoo_addon_project_task_sign-16.0.1.0.0.7.dist-info/WHEEL
odoo_addon_project_task_sign-16.0.1.0.0.7.dist-info/top_level.txt
odoo_addon_project_task_sign-16.0.1.0.0.7.dist-info/RECORD
