Metadata-Version: 2.1
Name: odoo-addon-project_task_sign
Version: 16.0.1.0.0.7
Requires-Python: >=3.10
Requires-Dist: odoo-addon-project_stock>=16.0dev,<16.1dev
Requires-Dist: odoo>=16.0a,<16.1dev
Summary: Sign tasks from portal.
Home-page: https://github.com/sygel-technology/sy-project
License: AGPL-3
Author: Sygel
Classifier: Programming Language :: Python
Classifier: Framework :: Odoo
Classifier: Framework :: Odoo :: 16.0
Classifier: License :: OSI Approved :: GNU Affero General Public License v3
